commands_gpt/__init__.py
commands_gpt/chat.py
commands_gpt/config.py
commands_gpt/models.py
commands_gpt/recognizers.py
commands_gpt/regex.py
commands_gpt/commands/__init__.py
commands_gpt/commands/commands_funcs.py
commands_gpt/commands/graphs.py
commands_gpt/util/__init__.py
commands_gpt/util/math_expr.py
commandsgpt-1.6.0.dist-info/LICENSE
commandsgpt-1.6.0.dist-info/METADATA
commandsgpt-1.6.0.dist-info/WHEEL
commandsgpt-1.6.0.dist-info/top_level.txt
commandsgpt-1.6.0.dist-info/RECORD
