Metadata-Version: 2.1
Name: commandsgpt
Version: 1.6.0
Summary: An implementation of GPT-4 that recognizes which commands it must run to fulfill an instruction, using a graph. Create new commands easily by describing them using natural language and coding the functions corresponding to the commands.
Home-page: https://github.com/AlexisAndradeDev/CommandsGPT
Author: Martín Alexis Martínez Andrade
Author-email: alexis.martinez.contacto@gmail.com
Project-URL: Bug Tracker, https://github.com/AlexisAndradeDev/CommandsGPT/issues
Project-URL: repository, https://github.com/AlexisAndradeDev/CommandsGPT
Classifier: License :: OSI Approved :: BSD License
Classifier: Operating System :: OS Independent
Classifier: Programming Language :: Python :: 3
Requires-Python: >=3.6
License-File: LICENSE
